precice_cli-1.0.0.dist-info/licenses/LICENSE
precicecli/cli.py
precicecli/native.py
precice_cli-1.0.0.dist-info/METADATA
precice_cli-1.0.0.dist-info/WHEEL
precice_cli-1.0.0.dist-info/entry_points.txt
precice_cli-1.0.0.dist-info/top_level.txt
precice_cli-1.0.0.dist-info/RECORD
