Metadata-Version: 2.4
Name: precice-cli
Version: 1.0.0
Summary: A unified command line interface for preCICE tools.
Author-email: The preCICE Developers <info@precice.org>
Maintainer-email: Frédéric Simonis <frederic.simonis@ipvs.uni-stuttgart.de>
License-Expression: MIT
Project-URL: Homepage, https://precice.org
Project-URL: Repository, https://github.com/precice/config-format.git
Project-URL: Bug Tracker, https://github.com/precice/config-format/issues
Keywords: preCICE,XML,configuration,format,visualization
Classifier: Development Status :: 4 - Beta
Classifier: Programming Language :: Python :: 3 :: Only
Classifier: Programming Language :: Python :: 3.8
Classifier: Topic :: Utilities
Requires-Python: >=3.8
License-File: LICENSE
Requires-Dist: precice-config-visualizer>=2
Requires-Dist: precice-config-format>=2
Requires-Dist: precice-profiling
Requires-Dist: precice-config-check
Requires-Dist: precice-case-generate
Dynamic: license-file
